shmessy/__init__.py
shmessy/date_utils.py
shmessy/exceptions.py
shmessy/schema.py
shmessy/types/__init__.py
shmessy/types/base.py
shmessy/types/boolean.py
shmessy/types/date.py
shmessy/types/datetime_.py
shmessy/types/email.py
shmessy/types/float.py
shmessy/types/integer.py
shmessy/types/ipv4_address.py
shmessy/types/string.py
shmessy/types/unix_timestamp.py
shmessy/types_handler.py
shmessy/utils.py
shmessy-2.0.3.dist-info/LICENSE
shmessy-2.0.3.dist-info/METADATA
shmessy-2.0.3.dist-info/WHEEL
shmessy-2.0.3.dist-info/RECORD
