Metadata-Version: 2.3
Name: shmessy
Version: 2.0.3
Summary: If your data is messy - Use Shmessy!
Author: Ohad Mata
Author-email: ohadmata@gmail.com
Requires-Python: >=3.9,<4.0
Classifier: Programming Language :: Python :: 3
Classifier: Programming Language :: Python :: 3.9
Classifier: Programming Language :: Python :: 3.10
Classifier: Programming Language :: Python :: 3.11
Classifier: Programming Language :: Python :: 3.12
Classifier: Programming Language :: Python :: 3.13
Requires-Dist: pandas (>=2.0)
Requires-Dist: pydantic[email] (>=1.10,<2.0)
Requires-Dist: tabulate (>=0.9)
Project-URL: Homepage, https://github.com/ohadmata/shmessy
Project-URL: Repository, https://github.com/ohadmata/shmessy
